Metadata-Version: 1.0
Name: lee-sndistributions
Version: 0.1
Summary: Gaussian distributions
Home-page: UNKNOWN
Author: louies lee
Author-email: UNKNOWN
License: UNKNOWN
Platform: UNKNOWN
